{
	"pools": [
		{
			"rolls": 1,
			"entries": [
				{
					"type": "minecraft:item",
					"name": "minecraft:cookie",
					"functions": [
						{
							"function": "minecraft:set_name",
							"name": {
								"italic": false,
								"translate": "item.cpp.peach_shaped_qiaoguo"
							}
						},
						{
							"function": "minecraft:set_lore",
							"replace": false,
							"lore": [
								{
									"italic": false,
									"color": "white",
									"font": "cpp:default",
									"text": "\u0099"
								},
								{
									"italic": false,
									"color": "dark_gray",
									"text": "cpp:peach_shaped_qiaoguo"
								},
								{
									"italic": false,
									"color": "gray",
									"translate": "text.cpp.weight_index",
									"with": [
										{
											"color": "green",
											"text": "-1"
										}
									]
								}
							]
						},
						{
							"function": "minecraft:set_nbt",
							"tag": "{id:'cpp:peach_shaped_qiaoguo',CustomModelData:12970205}"
						}
					]
				}
			]
		}
	]
}
